{
    "$schema": "https://schema.management.azure.com/schemas/2019-04-01/deploymentParameters.json#",
    "contentVersion": "1.0.0.0",
    "parameters": {
        "customer": {
            "value": "cloudone"
        },
        "environment": {
            "value": "dev"
        },
        "location": {
            "value": "usgovvirginia"
        },
        "automationAccountName": {
            "value": "splauto"
        },
        "configName": {
            "value": "CreateADPDC"
        },
        "script": {
            "value": "https://raw.githubusercontent.com/shawnadrockleonard/Azure/master/scripts/AzInventory/dsc/CreateADPDC.ps1"
        },
        "description": {
            "value": "minimum viable configuration for a DC promo"
        },
        "_artifactsLocationSasToken": {
            "value": ""
        }
    }
}